spade_anomaly_detection/Dockerfile
spade_anomaly_detection/__init__.py
spade_anomaly_detection/csv_data_loader.py
spade_anomaly_detection/data_loader.py
spade_anomaly_detection/occ_ensemble.py
spade_anomaly_detection/parameters.py
spade_anomaly_detection/requirements.txt
spade_anomaly_detection/runner.py
spade_anomaly_detection/supervised_model.py
spade_anomaly_detection/task.py
spade_anomaly_detection/colabs/spade_preprocessing.ipynb
spade_anomaly_detection/data_utils/__init__.py
spade_anomaly_detection/data_utils/bq_dataset.py
spade_anomaly_detection/data_utils/bq_dataset_test_utils.py
spade_anomaly_detection/data_utils/bq_utils.py
spade_anomaly_detection/data_utils/feature_metadata.py
spade_anomaly_detection/example_data/README.md
spade_anomaly_detection/example_data/covertype_pnu_10000.csv
spade_anomaly_detection/example_data/covertype_pnu_100000.csv
spade_anomaly_detection/example_data/covertype_pnu_train.csv
spade_anomaly_detection/example_data/covertype_pu_labeled.csv
spade_anomaly_detection/example_data/covertype_pu_train.csv
spade_anomaly_detection/example_data/covertype_test.csv
spade_anomaly_detection/example_data/drug_train_pu_labeled.csv
spade_anomaly_detection/example_data/thyroid_labeled.csv
spade_anomaly_detection/scripts/build_and_push_image.sh
spade_anomaly_detection/scripts/run_cloud_spade_experiment.sh
spade_anomaly_detection-0.4.0.dist-info/LICENSE
spade_anomaly_detection-0.4.0.dist-info/WHEEL
spade_anomaly_detection-0.4.0.dist-info/METADATA
spade_anomaly_detection-0.4.0.dist-info/RECORD
