Metadata-Version: 2.3
Name: spade_anomaly_detection
Version: 0.4.0
Summary: Semi-supervised Pseudo Labeler Anomaly Detection with Ensembling (SPADE) is a semi-supervised anomaly detection method that uses an ensemble of one class classifiers as the pseudo-labelers and supervised classifiers to achieve state of the art results especially on datasets with distribution mismatch between labeled and unlabeled samples.
Keywords: anomaly detection,ensemble model,one class classifiers
Author-email: spade_anomaly_detection authors <spade_anomaly_detection@google.com>
Requires-Python: >=3.8
Classifier: License :: OSI Approved :: Apache Software License
Classifier: Intended Audience :: Science/Research
Requires-Dist: absl-py==1.4.0
Requires-Dist: frozendict==2.3.2
Requires-Dist: joblib==1.2.0
Requires-Dist: pandas==2.2.2
Requires-Dist: pyarrow==14.0.1
Requires-Dist: retry==0.9.2
Requires-Dist: scikit-learn==1.4.2
Requires-Dist: tensorflow==2.12.1
Requires-Dist: tensorflow-datasets==4.9.6
Requires-Dist: parameterized==0.8.1
Requires-Dist: pytest==7.1.2
Requires-Dist: fastavro[codecs]==1.4.12
Requires-Dist: google-cloud-bigquery[pandas]==3.16.0
Requires-Dist: google-cloud-bigquery-storage[pandas, pyarrow, fastavro]==2.24.0
Requires-Dist: google-cloud-storage==2.14.0
Requires-Dist: cloudml-hypertune==0.1.0.dev6
Requires-Dist: tensorflow_decision_forests==1.3.0
Requires-Dist: pytest ; extra == "dev"
Requires-Dist: pytest-xdist ; extra == "dev"
Requires-Dist: pylint>=2.6.0 ; extra == "dev"
Requires-Dist: pyink ; extra == "dev"
Project-URL: changelog, https://github.com/google-research/spade_anomaly_detection/blob/main/CHANGELOG.md
Project-URL: homepage, https://github.com/google-research/spade_anomaly_detection
Project-URL: repository, https://github.com/google-research/spade_anomaly_detection
Provides-Extra: dev
